tootstagram/__init__.py
tootstagram/database.py
tootstagram/instagram.py
tootstagram/main.py
tootstagram/mastodon.py
tootstagram/utils.py
tootstagram-0.0.7.dist-info/LICENSE.md
tootstagram-0.0.7.dist-info/METADATA
tootstagram-0.0.7.dist-info/WHEEL
tootstagram-0.0.7.dist-info/entry_points.txt
tootstagram-0.0.7.dist-info/top_level.txt
tootstagram-0.0.7.dist-info/RECORD
