Metadata-Version: 2.1
Name: tootstagram
Version: 0.0.7
Summary: Duplicate posted images from Mastodon to Instagram
Author-email: Koen Martens <kmartens@sonologic.se>
Project-URL: Homepage, https://cvs.sonologic.net/gmc/nlgenerator
Project-URL: Bug Tracker, https://cvs.sonologic.net/gmc/nlgenerator/-/issues
Classifier: Programming Language :: Python :: 3
Classifier: Operating System :: OS Independent
Classifier: Development Status :: 3 - Alpha
Classifier: Environment :: Console
Requires-Python: >=3.8
License-File: LICENSE.md
Requires-Dist: instagrapi
Requires-Dist: Pillow (>=8.1.1)
Requires-Dist: toml
Requires-Dist: feedparser
